{"cameraMode":{"drawMode":0,"name":"Shaded","section":"Shading Mode"},"sceneLighting":true,"audioPlay":false,"sceneViewState":{"m_AlwaysRefresh":false,"showFog":true,"showSkybox":true,"showFlares":true,"showImageEffects":true,"showParticleSystems":true,"showVisualEffectGraphs":true,"m_FxEnabled":true},"in2DMode":false,"pivot":{"x":-3.643122673034668,"y":2.280075788497925,"z":-13.30732536315918},"rotation":{"x":-0.004504950251430273,"y":0.9305422306060791,"z":-0.011455154977738858,"w":-0.36596202850341799},"size":8.313088417053223,"orthographic":false}